imgkernelcad/__init__.py
imgkernelcad/data_load.py
imgkernelcad/features.py
imgkernelcad/main.py
imgkernelcad/programs.py
imgkernelcad-0.0.1.dist-info/METADATA
imgkernelcad-0.0.1.dist-info/WHEEL
imgkernelcad-0.0.1.dist-info/top_level.txt
imgkernelcad-0.0.1.dist-info/RECORD
